requests_aws_iam_auth/__init__.py
requests_aws_iam_auth/api_gateway.py
requests_aws_iam_auth-0.2.0.dist-info/LICENSE.txt
requests_aws_iam_auth-0.2.0.dist-info/METADATA
requests_aws_iam_auth-0.2.0.dist-info/WHEEL
requests_aws_iam_auth-0.2.0.dist-info/top_level.txt
requests_aws_iam_auth-0.2.0.dist-info/RECORD
