Metadata-Version: 2.1
Name: requests-aws-iam-auth
Version: 0.2.0
Summary: An AWS IAM authentication package for Requests. Supported services: API Gateway v1
Home-page: https://github.com/mateusamin/requests-aws-iam-auth/
Author: Mateus Amin, Bentron Drew
Author-email: mateus.amin@cleardata.com, bentron.drew@cleardata.com
License: UNKNOWN
Project-URL: Bug Tracker, https://github.com/mateusamin/requests-aws-iam-auth/issues
Project-URL: Documentation, https://github.com/MateusAmin/requests-aws-iam-auth/blob/master/README.md
Project-URL: Source Code, https://github.com/mateusamin/requests-aws-iam-auth/
Keywords: AWS IAM authentication auth AWS amazon API Gateway v1 Requests Signature v4
Platform: UNKNOWN
Classifier: Development Status :: 5 - Production/Stable
Classifier: Intended Audience :: Developers
Classifier: Intended Audience :: System Administrators
Classifier: Natural Language :: English
Classifier: License :: OSI Approved :: Apache Software License
Classifier: Programming Language :: Python
Classifier: Programming Language :: Python :: 3.6
Classifier: Programming Language :: Python :: 3.7
Classifier: Programming Language :: Python :: 3.8
Requires-Python: >=3.7.0
Requires-Dist: botocore (>=1.14.0)
Requires-Dist: requests (>=2.21.0)
